bweb/__init__.py
bweb/application.py
bweb/emailer.py
bweb/handler.py
bweb/patterns.py
bweb/route.py
bweb/route_map.py
bweb/urlspec.py
bweb/handlers/__init__.py
bweb/models/__init__.py
bweb/models/request_log.py
bweb/models/session.py
bweb/models/user.py
bweb/session/__init__.py
bweb/session/cookie_storage.py
bweb/session/database_storage.py
bweb/session/file_storage.py
bweb/session/memcache_storage.py
bweb-0.7.0.dist-info/METADATA
bweb-0.7.0.dist-info/RECORD
bweb-0.7.0.dist-info/WHEEL
bweb-0.7.0.dist-info/top_level.txt
