Metadata-Version: 2.1
Name: bweb
Version: 0.7.0
Summary: Black Earth’s web interface library
Home-page: https://github.com/BlackEarth/bweb
Author: Sean Harrison
Author-email: sah@blackearthgroup.com
License: LGPL 3.0
Platform: UNKNOWN
Classifier: Development Status :: 4 - Beta
Classifier: Intended Audience :: Developers
Classifier: License :: OSI Approved :: GNU Library or Lesser General Public License (LGPL)
Classifier: Programming Language :: Python :: 3
Provides-Extra: test
Provides-Extra: dev
Provides-Extra: dev
Provides-Extra: test
